AUTHORS
CHANGES
ChangeLog
LICENSE
MANIFEST.in
README
setup.cfg
setup.py
visa.py
docs/LICENSE
docs/Makefile
docs/architecture.rst
docs/backends.rst
docs/conf.py
docs/configuring.rst
docs/contributing.rst
docs/default.css
docs/example.rst
docs/faq.rst
docs/getting.rst
docs/getting_nivisa.rst
docs/index.rst
docs/make.bat
docs/migrating.rst
docs/names.rst
docs/resources.rst
docs/rvalues.rst
docs/shell.rst
docs/tutorial.rst
docs/_static/logo-full.jpg
docs/_templates/sidebarintro.html
docs/_templates/sidebarlogo.html
docs/_themes/.gitignore
docs/_themes/LICENSE
docs/_themes/README
docs/_themes/flask_theme_support.py
docs/_themes/flask/layout.html
docs/_themes/flask/relations.html
docs/_themes/flask/theme.conf
docs/_themes/flask/static/flasky.css_t
docs/_themes/flask/static/small_flask.css
docs/_themes/sphinx_rtd_theme/__init__.py
docs/_themes/sphinx_rtd_theme/breadcrumbs.html
docs/_themes/sphinx_rtd_theme/footer.html
docs/_themes/sphinx_rtd_theme/layout.html
docs/_themes/sphinx_rtd_theme/layout_old.html
docs/_themes/sphinx_rtd_theme/search.html
docs/_themes/sphinx_rtd_theme/searchbox.html
docs/_themes/sphinx_rtd_theme/theme.conf
docs/_themes/sphinx_rtd_theme/versions.html
docs/_themes/sphinx_rtd_theme/static/css/badge_only.css
docs/_themes/sphinx_rtd_theme/static/css/theme.css
docs/_themes/sphinx_rtd_theme/static/fonts/FontAwesome.otf
docs/_themes/sphinx_rtd_theme/static/fonts/fontawesome-webfont.eot
docs/_themes/sphinx_rtd_theme/static/fonts/fontawesome-webfont.svg
docs/_themes/sphinx_rtd_theme/static/fonts/fontawesome-webfont.ttf
docs/_themes/sphinx_rtd_theme/static/fonts/fontawesome-webfont.woff
docs/_themes/sphinx_rtd_theme/static/js/theme.js
docs/api/constants.rst
docs/api/index.rst
docs/api/resourcemanager.rst
docs/api/resources.rst
docs/api/visalibrarybase.rst
examples/itc4.py
examples/keithley2000.py
hedgehog_pyvisa.egg-info/PKG-INFO
hedgehog_pyvisa.egg-info/SOURCES.txt
hedgehog_pyvisa.egg-info/dependency_links.txt
hedgehog_pyvisa.egg-info/not-zip-safe
hedgehog_pyvisa.egg-info/top_level.txt
pyvisa/__init__.py
pyvisa/attributes.py
pyvisa/constants.py
pyvisa/errors.py
pyvisa/highlevel.py
pyvisa/rname.py
pyvisa/shell.py
pyvisa/util.py
