Metadata-Version: 1.1
Name: hedgehog-pyvisa
Version: 1.9.7
Summary: Python VISA bindings for GPIB, RS232, and USB instruments
Home-page: https://github.com/lordoftheflies/pyvisa
Author: lordoftheflies
Author-email: laszlo.hegedus@cherubits.hu
License: MIT License
Keywords: VISA GPIB USB serial RS232 measurement acquisition
Platform: Linux
Platform: Windows
Platform: Mac
Classifier: Development Status :: 5 - Production/Stable
Classifier: Intended Audience :: Developers
Classifier: Intended Audience :: Science/Research
Classifier: License :: OSI Approved :: MIT License
Classifier: Operating System :: Microsoft :: Windows
Classifier: Operating System :: POSIX :: Linux
Classifier: Operating System :: MacOS :: MacOS X
Classifier: Programming Language :: Python
Classifier: Topic :: Scientific/Engineering :: Interface Engine/Protocol Translator
Classifier: Topic :: Software Development :: Libraries :: Python Modules
Classifier: Programming Language :: Python :: 2.6
Classifier: Programming Language :: Python :: 2.7
Classifier: Programming Language :: Python :: 3.2
Classifier: Programming Language :: Python :: 3.3
Classifier: Programming Language :: Python :: 3.4
